<?xml version="1.0" encoding="UTF-8" standalone="yes"?><w:styles xmlns:mc="http://schemas.openxmlformats.org/markup-compatibility/2006" xmlns:o="urn:schemas-microsoft-com:office:office" xmlns:r="http://schemas.openxmlformats.org/officeDocument/2006/relationships" xmlns:m="http://schemas.openxmlformats.org/officeDocument/2006/math" xmlns:v="urn:schemas-microsoft-com:vml" xmlns:wp="http://schemas.openxmlformats.org/drawingml/2006/wordprocessingDrawing" xmlns:w10="urn:schemas-microsoft-com:office:word" xmlns:w="http://schemas.openxmlformats.org/wordprocessingml/2006/main" xmlns:wne="http://schemas.microsoft.com/office/word/2006/wordml" xmlns:sl="http://schemas.openxmlformats.org/schemaLibrary/2006/main" xmlns:a="http://schemas.openxmlformats.org/drawingml/2006/main" xmlns:pic="http://schemas.openxmlformats.org/drawingml/2006/picture" xmlns:c="http://schemas.openxmlformats.org/drawingml/2006/chart" xmlns:lc="http://schemas.openxmlformats.org/drawingml/2006/lockedCanvas" xmlns:dgm="http://schemas.openxmlformats.org/drawingml/2006/diagram" xmlns:wps="http://schemas.microsoft.com/office/word/2010/wordprocessingShape" xmlns:wpg="http://schemas.microsoft.com/office/word/2010/wordprocessingGroup" xmlns:w14="http://schemas.microsoft.com/office/word/2010/wordml" xmlns:w15="http://schemas.microsoft.com/office/word/2012/wordml" xmlns:w16="http://schemas.microsoft.com/office/word/2018/wordml" xmlns:w16cex="http://schemas.microsoft.com/office/word/2018/wordml/cex" xmlns:w16cid="http://schemas.microsoft.com/office/word/2016/wordml/cid" xmlns="http://schemas.microsoft.com/office/tasks/2019/documenttasks" xmlns:cr="http://schemas.microsoft.com/office/comments/2020/reactions"><w:docDefaults><w:rPrDefault><w:rPr><w:rFonts w:ascii="Calibri" w:cs="Calibri" w:eastAsia="Calibri" w:hAnsi="Calibri"/><w:lang w:val="ru"/></w:rPr></w:rPrDefault><w:pPrDefault><w:pPr/></w:pPrDefault></w:docDefaults><w:style w:type="table" w:styleId="TableNormal" w:default="1"><w:name w:val="TableNormal"/><w:tblPr><w:tblCellMar><w:top w:w="100.0" w:type="dxa"/><w:left w:w="100.0" w:type="dxa"/><w:bottom w:w="100.0" w:type="dxa"/><w:right w:w="100.0" w:type="dxa"/></w:tblCellMar></w:tblPr></w:style><w:style w:type="paragraph" w:styleId="Normal" w:default="1"><w:name w:val="normal"/></w:style><w:style w:type="paragraph" w:styleId="Heading1"><w:name w:val="heading 1"/><w:basedOn w:val="Normal"/><w:next w:val="Normal"/><w:pPr><w:keepNext w:val="1"/><w:keepLines w:val="1"/><w:pageBreakBefore w:val="0"/><w:spacing w:after="120" w:before="480" w:lineRule="auto"/></w:pPr><w:rPr><w:b w:val="1"/><w:sz w:val="48"/><w:szCs w:val="48"/></w:rPr></w:style><w:style w:type="paragraph" w:styleId="Heading2"><w:name w:val="heading 2"/><w:basedOn w:val="Normal"/><w:next w:val="Normal"/><w:pPr><w:keepNext w:val="1"/><w:keepLines w:val="1"/><w:pageBreakBefore w:val="0"/><w:spacing w:after="80" w:before="360" w:lineRule="auto"/></w:pPr><w:rPr><w:b w:val="1"/><w:sz w:val="36"/><w:szCs w:val="36"/></w:rPr></w:style><w:style w:type="paragraph" w:styleId="Heading3"><w:name w:val="heading 3"/><w:basedOn w:val="Normal"/><w:next w:val="Normal"/><w:pPr><w:keepNext w:val="1"/><w:keepLines w:val="1"/><w:pageBreakBefore w:val="0"/><w:spacing w:after="80" w:before="280" w:lineRule="auto"/></w:pPr><w:rPr><w:b w:val="1"/><w:sz w:val="28"/><w:szCs w:val="28"/></w:rPr></w:style><w:style w:type="paragraph" w:styleId="Heading4"><w:name w:val="heading 4"/><w:basedOn w:val="Normal"/><w:next w:val="Normal"/><w:pPr><w:keepNext w:val="1"/><w:keepLines w:val="1"/><w:pageBreakBefore w:val="0"/><w:spacing w:after="40" w:before="240" w:lineRule="auto"/></w:pPr><w:rPr><w:b w:val="1"/><w:sz w:val="24"/><w:szCs w:val="24"/></w:rPr></w:style><w:style w:type="paragraph" w:styleId="Heading5"><w:name w:val="heading 5"/><w:basedOn w:val="Normal"/><w:next w:val="Normal"/><w:pPr><w:keepNext w:val="1"/><w:keepLines w:val="1"/><w:pageBreakBefore w:val="0"/><w:spacing w:after="40" w:before="220" w:lineRule="auto"/></w:pPr><w:rPr><w:b w:val="1"/><w:sz w:val="22"/><w:szCs w:val="22"/></w:rPr></w:style><w:style w:type="paragraph" w:styleId="Heading6"><w:name w:val="heading 6"/><w:basedOn w:val="Normal"/><w:next w:val="Normal"/><w:pPr><w:keepNext w:val="1"/><w:keepLines w:val="1"/><w:pageBreakBefore w:val="0"/><w:spacing w:after="40" w:before="200" w:lineRule="auto"/></w:pPr><w:rPr><w:b w:val="1"/><w:sz w:val="20"/><w:szCs w:val="20"/></w:rPr></w:style><w:style w:type="paragraph" w:styleId="Title"><w:name w:val="Title"/><w:basedOn w:val="Normal"/><w:next w:val="Normal"/><w:pPr><w:keepNext w:val="1"/><w:keepLines w:val="1"/><w:pageBreakBefore w:val="0"/><w:spacing w:after="120" w:before="480" w:lineRule="auto"/></w:pPr><w:rPr><w:b w:val="1"/><w:sz w:val="72"/><w:szCs w:val="72"/></w:rPr></w:style><w:style w:type="paragraph" w:styleId="Обычный"><w:name w:val="Обычный"/><w:next w:val="Обычный"/><w:autoRedefine w:val="0"/><w:hidden w:val="0"/><w:qFormat w:val="0"/><w:pPr><w:suppressAutoHyphens w:val="1"/><w:spacing w:line="1" w:lineRule="atLeast"/><w:ind w:leftChars="-1" w:rightChars="0" w:firstLineChars="-1"/><w:textDirection w:val="btLr"/><w:textAlignment w:val="top"/><w:outlineLvl w:val="0"/></w:pPr><w:rPr><w:rFonts w:ascii="Times New Roman" w:eastAsia="Times New Roman" w:hAnsi="Times New Roman"/><w:w w:val="100"/><w:position w:val="-1"/><w:sz w:val="24"/><w:szCs w:val="24"/><w:effect w:val="none"/><w:vertAlign w:val="baseline"/><w:cs w:val="0"/><w:em w:val="none"/><w:lang w:bidi="ar-SA" w:eastAsia="ru-RU" w:val="ru-RU"/></w:rPr></w:style><w:style w:type="character" w:styleId="Основнойшрифтабзаца"><w:name w:val="Основной шрифт абзаца"/><w:next w:val="Основнойшрифтабзаца"/><w:autoRedefine w:val="0"/><w:hidden w:val="0"/><w:qFormat w:val="1"/><w:rPr><w:w w:val="100"/><w:position w:val="-1"/><w:effect w:val="none"/><w:vertAlign w:val="baseline"/><w:cs w:val="0"/><w:em w:val="none"/><w:lang/></w:rPr></w:style><w:style w:type="table" w:styleId="Обычнаятаблица"><w:name w:val="Обычная таблица"/><w:next w:val="Обычнаятаблица"/><w:autoRedefine w:val="0"/><w:hidden w:val="0"/><w:qFormat w:val="1"/><w:pPr><w:suppressAutoHyphens w:val="1"/><w:spacing w:line="1" w:lineRule="atLeast"/><w:ind w:leftChars="-1" w:rightChars="0" w:firstLineChars="-1"/><w:textDirection w:val="btLr"/><w:textAlignment w:val="top"/><w:outlineLvl w:val="0"/></w:pPr><w:rPr><w:w w:val="100"/><w:position w:val="-1"/><w:effect w:val="none"/><w:vertAlign w:val="baseline"/><w:cs w:val="0"/><w:em w:val="none"/><w:lang/></w:rPr><w:tblPr><w:jc w:val="left"/><w:tblInd w:w="0.0" w:type="dxa"/><w:tblCellMar><w:top w:w="0.0" w:type="dxa"/><w:left w:w="108.0" w:type="dxa"/><w:bottom w:w="0.0" w:type="dxa"/><w:right w:w="108.0" w:type="dxa"/></w:tblCellMar></w:tblPr></w:style><w:style w:type="numbering" w:styleId="Нетсписка"><w:name w:val="Нет списка"/><w:next w:val="Нетсписка"/><w:autoRedefine w:val="0"/><w:hidden w:val="0"/><w:qFormat w:val="1"/><w:pPr><w:suppressAutoHyphens w:val="1"/><w:spacing w:line="1" w:lineRule="atLeast"/><w:ind w:leftChars="-1" w:rightChars="0" w:firstLineChars="-1"/><w:textDirection w:val="btLr"/><w:textAlignment w:val="top"/><w:outlineLvl w:val="0"/></w:pPr></w:style><w:style w:type="paragraph" w:styleId="Текствыноски"><w:name w:val="Текст выноски"/><w:basedOn w:val="Обычный"/><w:next w:val="Текствыноски"/><w:autoRedefine w:val="0"/><w:hidden w:val="0"/><w:qFormat w:val="1"/><w:pPr><w:suppressAutoHyphens w:val="1"/><w:spacing w:line="1" w:lineRule="atLeast"/><w:ind w:leftChars="-1" w:rightChars="0" w:firstLineChars="-1"/><w:textDirection w:val="btLr"/><w:textAlignment w:val="top"/><w:outlineLvl w:val="0"/></w:pPr><w:rPr><w:rFonts w:ascii="Tahoma" w:cs="Tahoma" w:eastAsia="Times New Roman" w:hAnsi="Tahoma"/><w:w w:val="100"/><w:position w:val="-1"/><w:sz w:val="16"/><w:szCs w:val="16"/><w:effect w:val="none"/><w:vertAlign w:val="baseline"/><w:cs w:val="0"/><w:em w:val="none"/><w:lang w:bidi="ar-SA" w:eastAsia="ru-RU" w:val="ru-RU"/></w:rPr></w:style><w:style w:type="character" w:styleId="ТекствыноскиЗнак"><w:name w:val="Текст выноски Знак"/><w:next w:val="ТекствыноскиЗнак"/><w:autoRedefine w:val="0"/><w:hidden w:val="0"/><w:qFormat w:val="0"/><w:rPr><w:rFonts w:ascii="Tahoma" w:cs="Tahoma" w:eastAsia="Times New Roman" w:hAnsi="Tahoma"/><w:w w:val="100"/><w:position w:val="-1"/><w:sz w:val="16"/><w:szCs w:val="16"/><w:effect w:val="none"/><w:vertAlign w:val="baseline"/><w:cs w:val="0"/><w:em w:val="none"/><w:lang w:eastAsia="ru-RU"/></w:rPr></w:style><w:style w:type="table" w:styleId="Сеткатаблицы"><w:name w:val="Сетка таблицы"/><w:basedOn w:val="Обычнаятаблица"/><w:next w:val="Сеткатаблицы"/><w:autoRedefine w:val="0"/><w:hidden w:val="0"/><w:qFormat w:val="0"/><w:pPr><w:suppressAutoHyphens w:val="1"/><w:spacing w:line="1" w:lineRule="atLeast"/><w:ind w:leftChars="-1" w:rightChars="0" w:firstLineChars="-1"/><w:textDirection w:val="btLr"/><w:textAlignment w:val="top"/><w:outlineLvl w:val="0"/></w:pPr><w:rPr><w:w w:val="100"/><w:position w:val="-1"/><w:effect w:val="none"/><w:vertAlign w:val="baseline"/><w:cs w:val="0"/><w:em w:val="none"/><w:lang/></w:rPr><w:tblPr><w:tblStyle w:val="Сеткатаблицы"/><w:jc w:val="left"/><w:tblBorders><w:top w:color="000000" w:space="0" w:sz="4" w:val="single"/><w:left w:color="000000" w:space="0" w:sz="4" w:val="single"/><w:bottom w:color="000000" w:space="0" w:sz="4" w:val="single"/><w:right w:color="000000" w:space="0" w:sz="4" w:val="single"/><w:insideH w:color="000000" w:space="0" w:sz="4" w:val="single"/><w:insideV w:color="000000" w:space="0" w:sz="4" w:val="single"/></w:tblBorders></w:tblPr></w:style><w:style w:type="character" w:styleId="apple-converted-space"><w:name w:val="apple-converted-space"/><w:basedOn w:val="Основнойшрифтабзаца"/><w:next w:val="apple-converted-space"/><w:autoRedefine w:val="0"/><w:hidden w:val="0"/><w:qFormat w:val="0"/><w:rPr><w:w w:val="100"/><w:position w:val="-1"/><w:effect w:val="none"/><w:vertAlign w:val="baseline"/><w:cs w:val="0"/><w:em w:val="none"/><w:lang/></w:rPr></w:style><w:style w:type="character" w:styleId="Гиперссылка"><w:name w:val="Гиперссылка"/><w:next w:val="Гиперссылка"/><w:autoRedefine w:val="0"/><w:hidden w:val="0"/><w:qFormat w:val="1"/><w:rPr><w:color w:val="0000ff"/><w:w w:val="100"/><w:position w:val="-1"/><w:u w:val="single"/><w:effect w:val="none"/><w:vertAlign w:val="baseline"/><w:cs w:val="0"/><w:em w:val="none"/><w:lang/></w:rPr></w:style><w:style w:type="paragraph" w:styleId="Обычный(веб)"><w:name w:val="Обычный (веб)"/><w:basedOn w:val="Обычный"/><w:next w:val="Обычный(веб)"/><w:autoRedefine w:val="0"/><w:hidden w:val="0"/><w:qFormat w:val="1"/><w:pPr><w:suppressAutoHyphens w:val="1"/><w:spacing w:after="100" w:afterAutospacing="1" w:before="100" w:beforeAutospacing="1" w:line="1" w:lineRule="atLeast"/><w:ind w:leftChars="-1" w:rightChars="0" w:firstLineChars="-1"/><w:textDirection w:val="btLr"/><w:textAlignment w:val="top"/><w:outlineLvl w:val="0"/></w:pPr><w:rPr><w:rFonts w:ascii="Times New Roman" w:eastAsia="Times New Roman" w:hAnsi="Times New Roman"/><w:w w:val="100"/><w:position w:val="-1"/><w:sz w:val="24"/><w:szCs w:val="24"/><w:effect w:val="none"/><w:vertAlign w:val="baseline"/><w:cs w:val="0"/><w:em w:val="none"/><w:lang w:bidi="ar-SA" w:eastAsia="ru-RU" w:val="ru-RU"/></w:rPr></w:style><w:style w:type="character" w:styleId="Строгий"><w:name w:val="Строгий"/><w:next w:val="Строгий"/><w:autoRedefine w:val="0"/><w:hidden w:val="0"/><w:qFormat w:val="0"/><w:rPr><w:b w:val="1"/><w:bCs w:val="1"/><w:w w:val="100"/><w:position w:val="-1"/><w:effect w:val="none"/><w:vertAlign w:val="baseline"/><w:cs w:val="0"/><w:em w:val="none"/><w:lang/></w:rPr></w:style><w:style w:type="paragraph" w:styleId="Subtitle"><w:name w:val="Subtitle"/><w:basedOn w:val="Normal"/><w:next w:val="Normal"/><w:pPr><w:keepNext w:val="1"/><w:keepLines w:val="1"/><w:pageBreakBefore w:val="0"/><w:spacing w:after="80" w:before="360" w:lineRule="auto"/></w:pPr><w:rPr><w:rFonts w:ascii="Georgia" w:cs="Georgia" w:eastAsia="Georgia" w:hAnsi="Georgia"/><w:i w:val="1"/><w:color w:val="666666"/><w:sz w:val="48"/><w:szCs w:val="48"/></w:rPr></w:style><w:style w:type="table" w:styleId="Table1"><w:basedOn w:val="TableNormal"/><w:tblPr><w:tblStyleRowBandSize w:val="1"/><w:tblStyleColBandSize w:val="1"/><w:tblCellMar><w:top w:w="0.0" w:type="dxa"/><w:left w:w="108.0" w:type="dxa"/><w:bottom w:w="0.0" w:type="dxa"/><w:right w:w="108.0" w:type="dxa"/></w:tblCellMar></w:tblPr></w:style></w:styles>